softest/__init__.py
softest/case.py
softest/context.py
softest/support.py
softest-1.2.0.0.dist-info/METADATA
softest-1.2.0.0.dist-info/RECORD
softest-1.2.0.0.dist-info/WHEEL
softest-1.2.0.0.dist-info/top_level.txt
