Metadata-Version: 2.1
Name: softest
Version: 1.2.0.0
Summary: Supports lightweight soft assertions by extending the unittest.TestCase class
Home-page: http://privately.maintained.for.now
Author: Nick Umble
Author-email: privately.maintained@for.now
License: UNKNOWN
Platform: UNKNOWN
Classifier: Programming Language :: Python :: 3
Classifier: Development Status :: 5 - Production/Stable
Classifier: Environment :: Console
Classifier: Intended Audience :: Developers
Classifier: License :: Freeware
Classifier: Natural Language :: English
Classifier: Operating System :: OS Independent
Classifier: Topic :: Software Development :: Testing
